diktionary/__init__.py
diktionary/nested_default_dict.py
diktionary/nested_dict.py
diktionary/recursive_default_dict.py
diktionary-0.1.0.dist-info/WHEEL
diktionary-0.1.0.dist-info/METADATA
diktionary-0.1.0.dist-info/RECORD
