Metadata-Version: 2.1
Name: diktionary
Version: 0.1.0
Summary: Simple, zero-deps recursive default dictionary
Author: Gilad Barnea
Author-email: cr-gbarn-herolo@allot.com
Requires-Python: >=3.8,<4.0
Classifier: Programming Language :: Python :: 3
Classifier: Programming Language :: Python :: 3.8
Classifier: Programming Language :: Python :: 3.9
